LICENSE.txt
README.md
setup.cfg
setup.py
PyCorpKit.egg-info/PKG-INFO
PyCorpKit.egg-info/SOURCES.txt
PyCorpKit.egg-info/dependency_links.txt
PyCorpKit.egg-info/not-zip-safe
PyCorpKit.egg-info/requires.txt
PyCorpKit.egg-info/top_level.txt
src/__init__.py
src/account/__init__.py
src/account/urls.py
src/account/filters/__init__.py
src/account/filters/roles.py
src/account/filters/user.py
src/account/migrations/0001_initial.py
src/account/migrations/0002_initial.py
src/account/migrations/__init__.py
src/account/models/__init__.py
src/account/models/invitation.py
src/account/models/permission.py
src/account/models/role.py
src/account/models/signal.py
src/account/models/user.py
src/account/permissions/__init__.py
src/account/permissions/perms/__init__.py
src/account/permissions/perms/enforce.py
src/account/permissions/perms/apps/__init__.py
src/account/permissions/perms/apps/account.py
src/account/permissions/perms/apps/org_structure.py
src/account/permissions/perms/apps/perm_groups.py
src/account/permissions/perms/apps/setup.py
src/account/usecases/__init__.py
src/account/usecases/change_password.py
src/account/usecases/invitation.py
src/account/usecases/login.py
src/account/usecases/register.py
src/account/views/__init__.py
src/account/views/change_password.py
src/account/views/invitation.py
src/account/views/login.py
src/account/views/register.py
src/account/views/role.py
src/account/views/token.py
src/account/views/user.py
src/common/__init__.py
src/common/paginator.py
src/common/urls.py
src/common/filters/__init__.py
src/common/filters/base.py
src/common/filters/organisation.py
src/common/filters/profile.py
src/common/migrations/0001_initial.py
src/common/migrations/__init__.py
src/common/models/__init__.py
src/common/models/abstract.py
src/common/models/attachment.py
src/common/models/common.py
src/common/models/organisation.py
src/common/models/person.py
src/common/models/profile.py
src/common/models/signal.py
src/common/serializers/__init__.py
src/common/serializers/common.py
src/common/serializers/organisation.py
src/common/serializers/profile.py
src/common/usecases/__init__.py
src/common/usecases/organisation.py
src/common/usecases/profile.py
