Metadata-Version: 2.1
Name: PyCorpKit
Version: 0.0.0
Summary: Enterprise management library
Home-page: http://gitlab.com/
Author: PyCorpKit Backenders
Author-email: josemash4@gmail.com
Classifier: Environment :: Web Environment
Classifier: Framework :: Django :: 2.2
Classifier: Framework :: Django :: 3.0
Classifier: Framework :: Django :: 3.1
Classifier: Framework :: Django :: 3.2
Classifier: Framework :: Django :: 4.0
Classifier: Framework :: Django :: 5.0
Classifier: Intended Audience :: Developers
Classifier: License :: OSI Approved :: BSD License
Classifier: Operating System :: OS Independent
Classifier: Programming Language :: Python
Classifier: Programming Language :: Python :: 3.7
Classifier: Programming Language :: Python :: 3.8
Classifier: Programming Language :: Python :: 3.9
Classifier: Framework :: Django
Classifier: Topic :: Software Development :: Libraries :: Application Frameworks
Classifier: Topic :: Software Development :: Libraries :: Python Modules
License-File: LICENSE.txt
Requires-Dist: setuptools==75.1.0
Requires-Dist: Django==5.0.6
Requires-Dist: requests>=2.32.3
Requires-Dist: psycopg2-binary==2.9.9
Requires-Dist: djangorestframework==3.15.1
Requires-Dist: phonenumbers~=8.13.37
Requires-Dist: django-phonenumber-field~=7.3.0
Requires-Dist: django-filter==24.2
Requires-Dist: pytz==2024.1
Requires-Dist: gunicorn==22.0.0
Requires-Dist: boto3==1.34.127
Requires-Dist: django-cors-headers==4.3.1
Requires-Dist: celery==5.4.0
Requires-Dist: django_rest_passwordreset==1.4.1
Requires-Dist: djangorestframework-simplejwt==5.3.1
Requires-Dist: python-magic==0.4.27
Requires-Dist: django-anymail[sendgrid]
Requires-Dist: sentry-sdk==2.6.0
Requires-Dist: raven==6.10.0
Requires-Dist: django-extensions==3.2.3
Requires-Dist: drf-spectacular==0.27.2
Requires-Dist: whitenoise==6.7.0
Requires-Dist: PyJWT==2.9.0
Requires-Dist: django-storages==1.14.4
